discogs_tag/__init__.py
discogs_tag/cli.py
discogs_tag-1.6.2.dist-info/LICENSE
discogs_tag-1.6.2.dist-info/METADATA
discogs_tag-1.6.2.dist-info/WHEEL
discogs_tag-1.6.2.dist-info/entry_points.txt
discogs_tag-1.6.2.dist-info/RECORD
