Metadata-Version: 2.1
Name: discogs-tag
Version: 1.6.2
Summary: An audio tagger based on Discogs metadata.
Home-page: https://github.com/infojunkie/discogs-tag.py
Author: infojunkie
Author-email: karim.ratib@gmail.com
Requires-Python: >=3.10,<4.0
Classifier: Programming Language :: Python :: 3
Classifier: Programming Language :: Python :: 3.10
Classifier: Programming Language :: Python :: 3.11
Requires-Dist: fire (>=0.6.0,<0.7.0)
Requires-Dist: importlib-metadata (>=6.8.0,<7.0.0)
Requires-Dist: mutagen (>=1.46.0,<2.0.0)
Requires-Dist: pathvalidate (>=3.2.0,<4.0.0)
Requires-Dist: regex (>=2024.5.15,<2025.0.0)
Project-URL: Repository, https://github.com/infojunkie/discogs-tag.py
